{
	"$schema": "http://schema.management.azure.com/schemas/2015-01-01/deploymentTemplate.json#",
	"contentVersion": "1.0.0.0",
	"parameters": {
		"workspaceName": {
			"type": "string",
			"metadata": "Nom de l'espace de travail",
			"defaultValue": "oceananalyticsproject"
		},
		"AzureDataLakeStorage1_accountKey": {
			"type": "secureString",
			"metadata": "Chaîne sécurisée pour « accountKey » de « AzureDataLakeStorage1 »"
		},
		"AzureSynapseAnalytics1_password": {
			"type": "secureString",
			"metadata": "Chaîne sécurisée pour « password » de « AzureSynapseAnalytics1 »"
		},
		"CosmosDbNoSql_External_connectionString": {
			"type": "secureString",
			"metadata": "Chaîne sécurisée pour « connectionString » de « CosmosDbNoSql_External »"
		},
		"OceanAnalytics_CosmosDbNoSql_connectionString": {
			"type": "secureString",
			"metadata": "Chaîne sécurisée pour « connectionString » de « OceanAnalytics_CosmosDbNoSql »"
		},
		"oceananalyticsproject-WorkspaceDefaultSqlServer_connectionString": {
			"type": "secureString",
			"metadata": "Chaîne sécurisée pour « connectionString » de « oceananalyticsproject-WorkspaceDefaultSqlServer »",
			"defaultValue": "Integrated Security=False;Encrypt=True;Connection Timeout=30;Data Source=tcp:oceananalyticsproject.sql.azuresynapse.net,1433;Initial Catalog=@{linkedService().DBName}"
		},
		"AzureDataLakeStorage1_properties_typeProperties_url": {
			"type": "string",
			"defaultValue": "https://extremmapstorageaccount.dfs.core.windows.net/"
		},
		"AzureSynapseAnalytics1_properties_typeProperties_server": {
			"type": "string",
			"defaultValue": "oceananalyticsproject.sql.azuresynapse.net"
		},
		"AzureSynapseAnalytics1_properties_typeProperties_database": {
			"type": "string",
			"defaultValue": "poolSQL"
		},
		"AzureSynapseAnalytics1_properties_typeProperties_userName": {
			"type": "string",
			"defaultValue": "sqladminuser"
		},
		"WhalesApi_Linked_Service_properties_typeProperties_url": {
			"type": "string",
			"defaultValue": "https://api.obis.org/v3/"
		},
		"oceananalyticsproject-WorkspaceDefaultStorage_properties_typeProperties_url": {
			"type": "string",
			"defaultValue": "https://extremmapstorageaccount.dfs.core.windows.net"
		}
	},
	"variables": {
		"workspaceId": "[concat('Microsoft.Synapse/workspaces/', parameters('workspaceName'))]"
	},
	"resources": [
		{
			"name": "[concat(parameters('workspaceName'), '/CosmoDbToSqlDbSample')]",
			"type": "Microsoft.Synapse/workspaces/pipelines",
			"apiVersion": "2019-06-01-preview",
			"properties": {
				"activities": [
					{
						"name": "CosmoToSqlSampleDataFlow",
						"type": "ExecuteDataFlow",
						"dependsOn": [],
						"policy": {
							"timeout": "0.12:00:00",
							"retry": 0,
							"retryIntervalInSeconds": 30,
							"secureOutput": false,
							"secureInput": false
						},
						"userProperties": [],
						"typeProperties": {
							"dataflow": {
								"referenceName": "CosmoDbToObisWhalesSampleDB",
								"type": "DataFlowReference",
								"parameters": {},
								"datasetParameters": {
									"CosmosDbSql": {},
									"SampleDataBase": {}
								}
							},
							"staging": {},
							"compute": {
								"coreCount": 8,
								"computeType": "General"
							},
							"traceLevel": "Fine"
						}
					}
				],
				"policy": {
					"elapsedTimeMetric": {}
				},
				"annotations": []
			},
			"dependsOn": [
				"[concat(variables('workspaceId'), '/dataflows/CosmoDbToObisWhalesSampleDB')]"
			]
		},
		{
			"name": "[concat(parameters('workspaceName'), '/WhaleCsvToMongoDb')]",
			"type": "Microsoft.Synapse/workspaces/pipelines",
			"apiVersion": "2019-06-01-preview",
			"properties": {
				"activities": [
					{
						"name": "DataFlowWhales_CSV_Prod",
						"type": "ExecuteDataFlow",
						"dependsOn": [],
						"policy": {
							"timeout": "0.12:00:00",
							"retry": 0,
							"retryIntervalInSeconds": 30,
							"secureOutput": false,
							"secureInput": false
						},
						"userProperties": [],
						"typeProperties": {
							"dataflow": {
								"referenceName": "WhalesCsvToMongoDbTest",
								"type": "DataFlowReference",
								"parameters": {},
								"datasetParameters": {
									"WhalesCsv": {},
									"exporttocosmodb": {}
								}
							},
							"staging": {},
							"compute": {
								"coreCount": 8,
								"computeType": "General"
							},
							"traceLevel": "Fine"
						}
					}
				],
				"policy": {
					"elapsedTimeMetric": {}
				},
				"annotations": [],
				"lastPublishTime": "2024-11-22T00:15:17Z"
			},
			"dependsOn": [
				"[concat(variables('workspaceId'), '/dataflows/WhalesCsvToMongoDbTest')]"
			]
		},
		{
			"name": "[concat(parameters('workspaceName'), '/CosmosDbNoSqlContainerLink')]",
			"type": "Microsoft.Synapse/workspaces/datasets",
			"apiVersion": "2019-06-01-preview",
			"properties": {
				"linkedServiceName": {
					"referenceName": "OceanAnalytics_CosmosDbNoSql",
					"type": "LinkedServiceReference"
				},
				"annotations": [],
				"type": "CosmosDbSqlApiCollection",
				"schema": {},
				"typeProperties": {
					"collectionName": "whales_analytical_store"
				}
			},
			"dependsOn": [
				"[concat(variables('workspaceId'), '/linkedServices/OceanAnalytics_CosmosDbNoSql')]"
			]
		},
		{
			"name": "[concat(parameters('workspaceName'), '/DataFlowWhalesParquet')]",
			"type": "Microsoft.Synapse/workspaces/datasets",
			"apiVersion": "2019-06-01-preview",
			"properties": {
				"linkedServiceName": {
					"referenceName": "oceananalyticsproject-WorkspaceDefaultStorage",
					"type": "LinkedServiceReference"
				},
				"annotations": [],
				"type": "Parquet",
				"typeProperties": {
					"location": {
						"type": "AzureBlobFSLocation",
						"fileName": "parquetDb",
						"folderPath": "synapse/workspaces",
						"fileSystem": "ocean-analytics"
					},
					"compressionCodec": "snappy"
				},
				"schema": []
			},
			"dependsOn": [
				"[concat(variables('workspaceId'), '/linkedServices/oceananalyticsproject-WorkspaceDefaultStorage')]"
			]
		},
		{
			"name": "[concat(parameters('workspaceName'), '/WhalesApi_Input_Prod')]",
			"type": "Microsoft.Synapse/workspaces/datasets",
			"apiVersion": "2019-06-01-preview",
			"properties": {
				"linkedServiceName": {
					"referenceName": "WhalesApi_Linked_Service",
					"type": "LinkedServiceReference"
				},
				"annotations": [],
				"type": "RestResource",
				"typeProperties": {
					"relativeUrl": "occurrence?scientificname=Cetacea&startdate=2024-11-01&enddate=2024-11-21"
				},
				"schema": []
			},
			"dependsOn": [
				"[concat(variables('workspaceId'), '/linkedServices/WhalesApi_Linked_Service')]"
			]
		},
		{
			"name": "[concat(parameters('workspaceName'), '/WhalesCsv')]",
			"type": "Microsoft.Synapse/workspaces/datasets",
			"apiVersion": "2019-06-01-preview",
			"properties": {
				"linkedServiceName": {
					"referenceName": "oceananalyticsproject-WorkspaceDefaultStorage",
					"type": "LinkedServiceReference"
				},
				"annotations": [],
				"type": "DelimitedText",
				"typeProperties": {
					"location": {
						"type": "AzureBlobFSLocation",
						"fileName": "Occurrence.csv",
						"fileSystem": "ocean-analytics"
					},
					"columnDelimiter": ",",
					"escapeChar": "\\",
					"firstRowAsHeader": true,
					"quoteChar": "\""
				},
				"schema": [
					{
						"name": "id",
						"type": "String"
					},
					{
						"name": "dataset_id",
						"type": "String"
					},
					{
						"name": "decimallongitude",
						"type": "String"
					},
					{
						"name": "decimallatitude",
						"type": "String"
					},
					{
						"name": "date_start",
						"type": "String"
					},
					{
						"name": "date_mid",
						"type": "String"
					},
					{
						"name": "date_end",
						"type": "String"
					},
					{
						"name": "date_year",
						"type": "String"
					},
					{
						"name": "scientificname",
						"type": "String"
					},
					{
						"name": "originalscientificname",
						"type": "String"
					},
					{
						"name": "minimumdepthinmeters",
						"type": "String"
					},
					{
						"name": "maximumdepthinmeters",
						"type": "String"
					},
					{
						"name": "depth",
						"type": "String"
					},
					{
						"name": "coordinateuncertaintyinmeters",
						"type": "String"
					},
					{
						"name": "flags",
						"type": "String"
					},
					{
						"name": "dropped",
						"type": "String"
					},
					{
						"name": "absence",
						"type": "String"
					},
					{
						"name": "shoredistance",
						"type": "String"
					},
					{
						"name": "bathymetry",
						"type": "String"
					},
					{
						"name": "sst",
						"type": "String"
					},
					{
						"name": "sss",
						"type": "String"
					},
					{
						"name": "marine",
						"type": "String"
					},
					{
						"name": "brackish",
						"type": "String"
					},
					{
						"name": "freshwater",
						"type": "String"
					},
					{
						"name": "terrestrial",
						"type": "String"
					},
					{
						"name": "taxonrank",
						"type": "String"
					},
					{
						"name": "aphiaid",
						"type": "String"
					},
					{
						"name": "redlist_category",
						"type": "String"
					},
					{
						"name": "superdomain",
						"type": "String"
					},
					{
						"name": "domain",
						"type": "String"
					},
					{
						"name": "kingdom",
						"type": "String"
					},
					{
						"name": "subkingdom",
						"type": "String"
					},
					{
						"name": "infrakingdom",
						"type": "String"
					},
					{
						"name": "phylum",
						"type": "String"
					},
					{
						"name": "phylum_division",
						"type": "String"
					},
					{
						"name": "subphylum_subdivision",
						"type": "String"
					},
					{
						"name": "subphylum",
						"type": "String"
					},
					{
						"name": "infraphylum",
						"type": "String"
					},
					{
						"name": "parvphylum",
						"type": "String"
					},
					{
						"name": "gigaclass",
						"type": "String"
					},
					{
						"name": "megaclass",
						"type": "String"
					},
					{
						"name": "superclass",
						"type": "String"
					},
					{
						"name": "class",
						"type": "String"
					},
					{
						"name": "subclass",
						"type": "String"
					},
					{
						"name": "infraclass",
						"type": "String"
					},
					{
						"name": "subterclass",
						"type": "String"
					},
					{
						"name": "superorder",
						"type": "String"
					},
					{
						"name": "order",
						"type": "String"
					},
					{
						"name": "suborder",
						"type": "String"
					},
					{
						"name": "infraorder",
						"type": "String"
					},
					{
						"name": "parvorder",
						"type": "String"
					},
					{
						"name": "superfamily",
						"type": "String"
					},
					{
						"name": "family",
						"type": "String"
					},
					{
						"name": "subfamily",
						"type": "String"
					},
					{
						"name": "supertribe",
						"type": "String"
					},
					{
						"name": "tribe",
						"type": "String"
					},
					{
						"name": "subtribe",
						"type": "String"
					},
					{
						"name": "genus",
						"type": "String"
					},
					{
						"name": "subgenus",
						"type": "String"
					},
					{
						"name": "section",
						"type": "String"
					},
					{
						"name": "subsection",
						"type": "String"
					},
					{
						"name": "series",
						"type": "String"
					},
					{
						"name": "species",
						"type": "String"
					},
					{
						"name": "subspecies",
						"type": "String"
					},
					{
						"name": "natio",
						"type": "String"
					},
					{
						"name": "variety",
						"type": "String"
					},
					{
						"name": "subvariety",
						"type": "String"
					},
					{
						"name": "forma",
						"type": "String"
					},
					{
						"name": "subforma",
						"type": "String"
					},
					{
						"name": "type",
						"type": "String"
					},
					{
						"name": "modified",
						"type": "String"
					},
					{
						"name": "language",
						"type": "String"
					},
					{
						"name": "license",
						"type": "String"
					},
					{
						"name": "rightsholder",
						"type": "String"
					},
					{
						"name": "accessrights",
						"type": "String"
					},
					{
						"name": "bibliographiccitation",
						"type": "String"
					},
					{
						"name": "references",
						"type": "String"
					},
					{
						"name": "institutionid",
						"type": "String"
					},
					{
						"name": "collectionid",
						"type": "String"
					},
					{
						"name": "datasetid",
						"type": "String"
					},
					{
						"name": "institutioncode",
						"type": "String"
					},
					{
						"name": "collectioncode",
						"type": "String"
					},
					{
						"name": "datasetname",
						"type": "String"
					},
					{
						"name": "ownerinstitutioncode",
						"type": "String"
					},
					{
						"name": "basisofrecord",
						"type": "String"
					},
					{
						"name": "informationwithheld",
						"type": "String"
					},
					{
						"name": "datageneralizations",
						"type": "String"
					},
					{
						"name": "dynamicproperties",
						"type": "String"
					},
					{
						"name": "materialsampleid",
						"type": "String"
					},
					{
						"name": "occurrenceid",
						"type": "String"
					},
					{
						"name": "catalognumber",
						"type": "String"
					},
					{
						"name": "occurrenceremarks",
						"type": "String"
					},
					{
						"name": "recordnumber",
						"type": "String"
					},
					{
						"name": "recordedby",
						"type": "String"
					},
					{
						"name": "recordedbyid",
						"type": "String"
					},
					{
						"name": "individualcount",
						"type": "String"
					},
					{
						"name": "organismquantity",
						"type": "String"
					},
					{
						"name": "organismquantitytype",
						"type": "String"
					},
					{
						"name": "sex",
						"type": "String"
					},
					{
						"name": "lifestage",
						"type": "String"
					},
					{
						"name": "reproductivecondition",
						"type": "String"
					},
					{
						"name": "behavior",
						"type": "String"
					},
					{
						"name": "establishmentmeans",
						"type": "String"
					},
					{
						"name": "occurrencestatus",
						"type": "String"
					},
					{
						"name": "preparations",
						"type": "String"
					},
					{
						"name": "disposition",
						"type": "String"
					},
					{
						"name": "othercatalognumbers",
						"type": "String"
					},
					{
						"name": "associatedmedia",
						"type": "String"
					},
					{
						"name": "associatedreferences",
						"type": "String"
					},
					{
						"name": "associatedsequences",
						"type": "String"
					},
					{
						"name": "associatedtaxa",
						"type": "String"
					},
					{
						"name": "organismid",
						"type": "String"
					},
					{
						"name": "organismname",
						"type": "String"
					},
					{
						"name": "organismscope",
						"type": "String"
					},
					{
						"name": "associatedoccurrences",
						"type": "String"
					},
					{
						"name": "associatedorganisms",
						"type": "String"
					},
					{
						"name": "previousidentifications",
						"type": "String"
					},
					{
						"name": "organismremarks",
						"type": "String"
					},
					{
						"name": "eventid",
						"type": "String"
					},
					{
						"name": "parenteventid",
						"type": "String"
					},
					{
						"name": "samplingprotocol",
						"type": "String"
					},
					{
						"name": "samplesizevalue",
						"type": "String"
					},
					{
						"name": "samplesizeunit",
						"type": "String"
					},
					{
						"name": "samplingeffort",
						"type": "String"
					},
					{
						"name": "eventdate",
						"type": "String"
					},
					{
						"name": "eventtime",
						"type": "String"
					},
					{
						"name": "startdayofyear",
						"type": "String"
					},
					{
						"name": "enddayofyear",
						"type": "String"
					},
					{
						"name": "year",
						"type": "String"
					},
					{
						"name": "month",
						"type": "String"
					},
					{
						"name": "day",
						"type": "String"
					},
					{
						"name": "verbatimeventdate",
						"type": "String"
					},
					{
						"name": "habitat",
						"type": "String"
					},
					{
						"name": "fieldnumber",
						"type": "String"
					},
					{
						"name": "fieldnotes",
						"type": "String"
					},
					{
						"name": "eventremarks",
						"type": "String"
					},
					{
						"name": "locationid",
						"type": "String"
					},
					{
						"name": "highergeographyid",
						"type": "String"
					},
					{
						"name": "highergeography",
						"type": "String"
					},
					{
						"name": "continent",
						"type": "String"
					},
					{
						"name": "waterbody",
						"type": "String"
					},
					{
						"name": "islandgroup",
						"type": "String"
					},
					{
						"name": "island",
						"type": "String"
					},
					{
						"name": "country",
						"type": "String"
					},
					{
						"name": "countrycode",
						"type": "String"
					},
					{
						"name": "stateprovince",
						"type": "String"
					},
					{
						"name": "county",
						"type": "String"
					},
					{
						"name": "municipality",
						"type": "String"
					},
					{
						"name": "locality",
						"type": "String"
					},
					{
						"name": "verbatimlocality",
						"type": "String"
					},
					{
						"name": "verbatimelevation",
						"type": "String"
					},
					{
						"name": "minimumelevationinmeters",
						"type": "String"
					},
					{
						"name": "maximumelevationinmeters",
						"type": "String"
					},
					{
						"name": "verbatimdepth",
						"type": "String"
					},
					{
						"name": "minimumdistanceabovesurfaceinmeters",
						"type": "String"
					},
					{
						"name": "maximumdistanceabovesurfaceinmeters",
						"type": "String"
					},
					{
						"name": "locationaccordingto",
						"type": "String"
					},
					{
						"name": "locationremarks",
						"type": "String"
					},
					{
						"name": "verbatimcoordinates",
						"type": "String"
					},
					{
						"name": "verbatimlatitude",
						"type": "String"
					},
					{
						"name": "verbatimlongitude",
						"type": "String"
					},
					{
						"name": "verbatimcoordinatesystem",
						"type": "String"
					},
					{
						"name": "verbatimsrs",
						"type": "String"
					},
					{
						"name": "geodeticdatum",
						"type": "String"
					},
					{
						"name": "coordinateprecision",
						"type": "String"
					},
					{
						"name": "pointradiusspatialfit",
						"type": "String"
					},
					{
						"name": "footprintwkt",
						"type": "String"
					},
					{
						"name": "footprintsrs",
						"type": "String"
					},
					{
						"name": "footprintspatialfit",
						"type": "String"
					},
					{
						"name": "georeferencedby",
						"type": "String"
					},
					{
						"name": "georeferenceddate",
						"type": "String"
					},
					{
						"name": "georeferenceprotocol",
						"type": "String"
					},
					{
						"name": "georeferencesources",
						"type": "String"
					},
					{
						"name": "georeferenceverificationstatus",
						"type": "String"
					},
					{
						"name": "georeferenceremarks",
						"type": "String"
					},
					{
						"name": "geologicalcontextid",
						"type": "String"
					},
					{
						"name": "earliesteonorlowesteonothem",
						"type": "String"
					},
					{
						"name": "latesteonorhighesteonothem",
						"type": "String"
					},
					{
						"name": "earliesteraorlowesterathem",
						"type": "String"
					},
					{
						"name": "latesteraorhighesterathem",
						"type": "String"
					},
					{
						"name": "earliestperiodorlowestsystem",
						"type": "String"
					},
					{
						"name": "latestperiodorhighestsystem",
						"type": "String"
					},
					{
						"name": "earliestepochorlowestseries",
						"type": "String"
					},
					{
						"name": "latestepochorhighestseries",
						"type": "String"
					},
					{
						"name": "earliestageorloweststage",
						"type": "String"
					},
					{
						"name": "latestageorhigheststage",
						"type": "String"
					},
					{
						"name": "lowestbiostratigraphiczone",
						"type": "String"
					},
					{
						"name": "highestbiostratigraphiczone",
						"type": "String"
					},
					{
						"name": "lithostratigraphicterms",
						"type": "String"
					},
					{
						"name": "group",
						"type": "String"
					},
					{
						"name": "formation",
						"type": "String"
					},
					{
						"name": "member",
						"type": "String"
					},
					{
						"name": "bed",
						"type": "String"
					},
					{
						"name": "identificationid",
						"type": "String"
					},
					{
						"name": "identifiedby",
						"type": "String"
					},
					{
						"name": "identifiedbyid",
						"type": "String"
					},
					{
						"name": "dateidentified",
						"type": "String"
					},
					{
						"name": "identificationreferences",
						"type": "String"
					},
					{
						"name": "identificationremarks",
						"type": "String"
					},
					{
						"name": "identificationqualifier",
						"type": "String"
					},
					{
						"name": "identificationverificationstatus",
						"type": "String"
					},
					{
						"name": "typestatus",
						"type": "String"
					},
					{
						"name": "taxonid",
						"type": "String"
					},
					{
						"name": "scientificnameid",
						"type": "String"
					},
					{
						"name": "acceptednameusageid",
						"type": "String"
					},
					{
						"name": "parentnameusageid",
						"type": "String"
					},
					{
						"name": "originalnameusageid",
						"type": "String"
					},
					{
						"name": "nameaccordingtoid",
						"type": "String"
					},
					{
						"name": "namepublishedinid",
						"type": "String"
					},
					{
						"name": "taxonconceptid",
						"type": "String"
					},
					{
						"name": "acceptednameusage",
						"type": "String"
					},
					{
						"name": "parentnameusage",
						"type": "String"
					},
					{
						"name": "originalnameusage",
						"type": "String"
					},
					{
						"name": "nameaccordingto",
						"type": "String"
					},
					{
						"name": "namepublishedin",
						"type": "String"
					},
					{
						"name": "namepublishedinyear",
						"type": "String"
					},
					{
						"name": "higherclassification",
						"type": "String"
					},
					{
						"name": "specificepithet",
						"type": "String"
					},
					{
						"name": "infraspecificepithet",
						"type": "String"
					},
					{
						"name": "verbatimtaxonrank",
						"type": "String"
					},
					{
						"name": "scientificnameauthorship",
						"type": "String"
					},
					{
						"name": "vernacularname",
						"type": "String"
					},
					{
						"name": "nomenclaturalcode",
						"type": "String"
					},
					{
						"name": "taxonomicstatus",
						"type": "String"
					},
					{
						"name": "nomenclaturalstatus",
						"type": "String"
					},
					{
						"name": "taxonremarks",
						"type": "String"
					}
				]
			},
			"dependsOn": [
				"[concat(variables('workspaceId'), '/linkedServices/oceananalyticsproject-WorkspaceDefaultStorage')]"
			]
		},
		{
			"name": "[concat(parameters('workspaceName'), '/WhalesOccurence_Prod')]",
			"type": "Microsoft.Synapse/workspaces/datasets",
			"apiVersion": "2019-06-01-preview",
			"properties": {
				"linkedServiceName": {
					"referenceName": "oceananalyticsproject-WorkspaceDefaultStorage",
					"type": "LinkedServiceReference"
				},
				"annotations": [],
				"type": "DelimitedText",
				"typeProperties": {
					"location": {
						"type": "AzureBlobFSLocation",
						"fileName": "AllWhalesCsvOccurence.csv",
						"fileSystem": "ocean-analytics"
					},
					"columnDelimiter": ",",
					"escapeChar": "\\",
					"firstRowAsHeader": true,
					"quoteChar": "\""
				},
				"schema": [
					{
						"name": "id",
						"type": "String"
					},
					{
						"name": "dataset_id",
						"type": "String"
					},
					{
						"name": "decimallongitude",
						"type": "String"
					},
					{
						"name": "decimallatitude",
						"type": "String"
					},
					{
						"name": "date_start",
						"type": "String"
					},
					{
						"name": "date_mid",
						"type": "String"
					},
					{
						"name": "date_end",
						"type": "String"
					},
					{
						"name": "date_year",
						"type": "String"
					},
					{
						"name": "scientificname",
						"type": "String"
					},
					{
						"name": "originalscientificname",
						"type": "String"
					},
					{
						"name": "minimumdepthinmeters",
						"type": "String"
					},
					{
						"name": "maximumdepthinmeters",
						"type": "String"
					},
					{
						"name": "depth",
						"type": "String"
					},
					{
						"name": "coordinateuncertaintyinmeters",
						"type": "String"
					},
					{
						"name": "flags",
						"type": "String"
					},
					{
						"name": "dropped",
						"type": "String"
					},
					{
						"name": "absence",
						"type": "String"
					},
					{
						"name": "shoredistance",
						"type": "String"
					},
					{
						"name": "bathymetry",
						"type": "String"
					},
					{
						"name": "sst",
						"type": "String"
					},
					{
						"name": "sss",
						"type": "String"
					},
					{
						"name": "marine",
						"type": "String"
					},
					{
						"name": "brackish",
						"type": "String"
					},
					{
						"name": "freshwater",
						"type": "String"
					},
					{
						"name": "terrestrial",
						"type": "String"
					},
					{
						"name": "taxonrank",
						"type": "String"
					},
					{
						"name": "aphiaid",
						"type": "String"
					},
					{
						"name": "redlist_category",
						"type": "String"
					},
					{
						"name": "superdomain",
						"type": "String"
					},
					{
						"name": "domain",
						"type": "String"
					},
					{
						"name": "kingdom",
						"type": "String"
					},
					{
						"name": "subkingdom",
						"type": "String"
					},
					{
						"name": "infrakingdom",
						"type": "String"
					},
					{
						"name": "phylum",
						"type": "String"
					},
					{
						"name": "phylum_division",
						"type": "String"
					},
					{
						"name": "subphylum_subdivision",
						"type": "String"
					},
					{
						"name": "subphylum",
						"type": "String"
					},
					{
						"name": "infraphylum",
						"type": "String"
					},
					{
						"name": "parvphylum",
						"type": "String"
					},
					{
						"name": "gigaclass",
						"type": "String"
					},
					{
						"name": "megaclass",
						"type": "String"
					},
					{
						"name": "superclass",
						"type": "String"
					},
					{
						"name": "class",
						"type": "String"
					},
					{
						"name": "subclass",
						"type": "String"
					},
					{
						"name": "infraclass",
						"type": "String"
					},
					{
						"name": "subterclass",
						"type": "String"
					},
					{
						"name": "superorder",
						"type": "String"
					},
					{
						"name": "order",
						"type": "String"
					},
					{
						"name": "suborder",
						"type": "String"
					},
					{
						"name": "infraorder",
						"type": "String"
					},
					{
						"name": "parvorder",
						"type": "String"
					},
					{
						"name": "superfamily",
						"type": "String"
					},
					{
						"name": "family",
						"type": "String"
					},
					{
						"name": "subfamily",
						"type": "String"
					},
					{
						"name": "supertribe",
						"type": "String"
					},
					{
						"name": "tribe",
						"type": "String"
					},
					{
						"name": "subtribe",
						"type": "String"
					},
					{
						"name": "genus",
						"type": "String"
					},
					{
						"name": "subgenus",
						"type": "String"
					},
					{
						"name": "section",
						"type": "String"
					},
					{
						"name": "subsection",
						"type": "String"
					},
					{
						"name": "series",
						"type": "String"
					},
					{
						"name": "species",
						"type": "String"
					},
					{
						"name": "subspecies",
						"type": "String"
					},
					{
						"name": "natio",
						"type": "String"
					},
					{
						"name": "variety",
						"type": "String"
					},
					{
						"name": "subvariety",
						"type": "String"
					},
					{
						"name": "forma",
						"type": "String"
					},
					{
						"name": "subforma",
						"type": "String"
					},
					{
						"name": "type",
						"type": "String"
					},
					{
						"name": "modified",
						"type": "String"
					},
					{
						"name": "language",
						"type": "String"
					},
					{
						"name": "license",
						"type": "String"
					},
					{
						"name": "rightsholder",
						"type": "String"
					},
					{
						"name": "accessrights",
						"type": "String"
					},
					{
						"name": "bibliographiccitation",
						"type": "String"
					},
					{
						"name": "references",
						"type": "String"
					},
					{
						"name": "institutionid",
						"type": "String"
					},
					{
						"name": "collectionid",
						"type": "String"
					},
					{
						"name": "datasetid",
						"type": "String"
					},
					{
						"name": "institutioncode",
						"type": "String"
					},
					{
						"name": "collectioncode",
						"type": "String"
					},
					{
						"name": "datasetname",
						"type": "String"
					},
					{
						"name": "ownerinstitutioncode",
						"type": "String"
					},
					{
						"name": "basisofrecord",
						"type": "String"
					},
					{
						"name": "informationwithheld",
						"type": "String"
					},
					{
						"name": "datageneralizations",
						"type": "String"
					},
					{
						"name": "dynamicproperties",
						"type": "String"
					},
					{
						"name": "materialsampleid",
						"type": "String"
					},
					{
						"name": "occurrenceid",
						"type": "String"
					},
					{
						"name": "catalognumber",
						"type": "String"
					},
					{
						"name": "occurrenceremarks",
						"type": "String"
					},
					{
						"name": "recordnumber",
						"type": "String"
					},
					{
						"name": "recordedby",
						"type": "String"
					},
					{
						"name": "recordedbyid",
						"type": "String"
					},
					{
						"name": "individualcount",
						"type": "String"
					},
					{
						"name": "organismquantity",
						"type": "String"
					},
					{
						"name": "organismquantitytype",
						"type": "String"
					},
					{
						"name": "sex",
						"type": "String"
					},
					{
						"name": "lifestage",
						"type": "String"
					},
					{
						"name": "reproductivecondition",
						"type": "String"
					},
					{
						"name": "behavior",
						"type": "String"
					},
					{
						"name": "establishmentmeans",
						"type": "String"
					},
					{
						"name": "occurrencestatus",
						"type": "String"
					},
					{
						"name": "preparations",
						"type": "String"
					},
					{
						"name": "disposition",
						"type": "String"
					},
					{
						"name": "othercatalognumbers",
						"type": "String"
					},
					{
						"name": "associatedmedia",
						"type": "String"
					},
					{
						"name": "associatedreferences",
						"type": "String"
					},
					{
						"name": "associatedsequences",
						"type": "String"
					},
					{
						"name": "associatedtaxa",
						"type": "String"
					},
					{
						"name": "organismid",
						"type": "String"
					},
					{
						"name": "organismname",
						"type": "String"
					},
					{
						"name": "organismscope",
						"type": "String"
					},
					{
						"name": "associatedoccurrences",
						"type": "String"
					},
					{
						"name": "associatedorganisms",
						"type": "String"
					},
					{
						"name": "previousidentifications",
						"type": "String"
					},
					{
						"name": "organismremarks",
						"type": "String"
					},
					{
						"name": "eventid",
						"type": "String"
					},
					{
						"name": "parenteventid",
						"type": "String"
					},
					{
						"name": "samplingprotocol",
						"type": "String"
					},
					{
						"name": "samplesizevalue",
						"type": "String"
					},
					{
						"name": "samplesizeunit",
						"type": "String"
					},
					{
						"name": "samplingeffort",
						"type": "String"
					},
					{
						"name": "eventdate",
						"type": "String"
					},
					{
						"name": "eventtime",
						"type": "String"
					},
					{
						"name": "startdayofyear",
						"type": "String"
					},
					{
						"name": "enddayofyear",
						"type": "String"
					},
					{
						"name": "year",
						"type": "String"
					},
					{
						"name": "month",
						"type": "String"
					},
					{
						"name": "day",
						"type": "String"
					},
					{
						"name": "verbatimeventdate",
						"type": "String"
					},
					{
						"name": "habitat",
						"type": "String"
					},
					{
						"name": "fieldnumber",
						"type": "String"
					},
					{
						"name": "fieldnotes",
						"type": "String"
					},
					{
						"name": "eventremarks",
						"type": "String"
					},
					{
						"name": "locationid",
						"type": "String"
					},
					{
						"name": "highergeographyid",
						"type": "String"
					},
					{
						"name": "highergeography",
						"type": "String"
					},
					{
						"name": "continent",
						"type": "String"
					},
					{
						"name": "waterbody",
						"type": "String"
					},
					{
						"name": "islandgroup",
						"type": "String"
					},
					{
						"name": "island",
						"type": "String"
					},
					{
						"name": "country",
						"type": "String"
					},
					{
						"name": "countrycode",
						"type": "String"
					},
					{
						"name": "stateprovince",
						"type": "String"
					},
					{
						"name": "county",
						"type": "String"
					},
					{
						"name": "municipality",
						"type": "String"
					},
					{
						"name": "locality",
						"type": "String"
					},
					{
						"name": "verbatimlocality",
						"type": "String"
					},
					{
						"name": "verbatimelevation",
						"type": "String"
					},
					{
						"name": "minimumelevationinmeters",
						"type": "String"
					},
					{
						"name": "maximumelevationinmeters",
						"type": "String"
					},
					{
						"name": "verbatimdepth",
						"type": "String"
					},
					{
						"name": "minimumdistanceabovesurfaceinmeters",
						"type": "String"
					},
					{
						"name": "maximumdistanceabovesurfaceinmeters",
						"type": "String"
					},
					{
						"name": "locationaccordingto",
						"type": "String"
					},
					{
						"name": "locationremarks",
						"type": "String"
					},
					{
						"name": "verbatimcoordinates",
						"type": "String"
					},
					{
						"name": "verbatimlatitude",
						"type": "String"
					},
					{
						"name": "verbatimlongitude",
						"type": "String"
					},
					{
						"name": "verbatimcoordinatesystem",
						"type": "String"
					},
					{
						"name": "verbatimsrs",
						"type": "String"
					},
					{
						"name": "geodeticdatum",
						"type": "String"
					},
					{
						"name": "coordinateprecision",
						"type": "String"
					},
					{
						"name": "pointradiusspatialfit",
						"type": "String"
					},
					{
						"name": "footprintwkt",
						"type": "String"
					},
					{
						"name": "footprintsrs",
						"type": "String"
					},
					{
						"name": "footprintspatialfit",
						"type": "String"
					},
					{
						"name": "georeferencedby",
						"type": "String"
					},
					{
						"name": "georeferenceddate",
						"type": "String"
					},
					{
						"name": "georeferenceprotocol",
						"type": "String"
					},
					{
						"name": "georeferencesources",
						"type": "String"
					},
					{
						"name": "georeferenceverificationstatus",
						"type": "String"
					},
					{
						"name": "georeferenceremarks",
						"type": "String"
					},
					{
						"name": "geologicalcontextid",
						"type": "String"
					},
					{
						"name": "earliesteonorlowesteonothem",
						"type": "String"
					},
					{
						"name": "latesteonorhighesteonothem",
						"type": "String"
					},
					{
						"name": "earliesteraorlowesterathem",
						"type": "String"
					},
					{
						"name": "latesteraorhighesterathem",
						"type": "String"
					},
					{
						"name": "earliestperiodorlowestsystem",
						"type": "String"
					},
					{
						"name": "latestperiodorhighestsystem",
						"type": "String"
					},
					{
						"name": "earliestepochorlowestseries",
						"type": "String"
					},
					{
						"name": "latestepochorhighestseries",
						"type": "String"
					},
					{
						"name": "earliestageorloweststage",
						"type": "String"
					},
					{
						"name": "latestageorhigheststage",
						"type": "String"
					},
					{
						"name": "lowestbiostratigraphiczone",
						"type": "String"
					},
					{
						"name": "highestbiostratigraphiczone",
						"type": "String"
					},
					{
						"name": "lithostratigraphicterms",
						"type": "String"
					},
					{
						"name": "group",
						"type": "String"
					},
					{
						"name": "formation",
						"type": "String"
					},
					{
						"name": "member",
						"type": "String"
					},
					{
						"name": "bed",
						"type": "String"
					},
					{
						"name": "identificationid",
						"type": "String"
					},
					{
						"name": "identifiedby",
						"type": "String"
					},
					{
						"name": "identifiedbyid",
						"type": "String"
					},
					{
						"name": "dateidentified",
						"type": "String"
					},
					{
						"name": "identificationreferences",
						"type": "String"
					},
					{
						"name": "identificationremarks",
						"type": "String"
					},
					{
						"name": "identificationqualifier",
						"type": "String"
					},
					{
						"name": "identificationverificationstatus",
						"type": "String"
					},
					{
						"name": "typestatus",
						"type": "String"
					},
					{
						"name": "taxonid",
						"type": "String"
					},
					{
						"name": "scientificnameid",
						"type": "String"
					},
					{
						"name": "acceptednameusageid",
						"type": "String"
					},
					{
						"name": "parentnameusageid",
						"type": "String"
					},
					{
						"name": "originalnameusageid",
						"type": "String"
					},
					{
						"name": "nameaccordingtoid",
						"type": "String"
					},
					{
						"name": "namepublishedinid",
						"type": "String"
					},
					{
						"name": "taxonconceptid",
						"type": "String"
					},
					{
						"name": "acceptednameusage",
						"type": "String"
					},
					{
						"name": "parentnameusage",
						"type": "String"
					},
					{
						"name": "originalnameusage",
						"type": "String"
					},
					{
						"name": "nameaccordingto",
						"type": "String"
					},
					{
						"name": "namepublishedin",
						"type": "String"
					},
					{
						"name": "namepublishedinyear",
						"type": "String"
					},
					{
						"name": "higherclassification",
						"type": "String"
					},
					{
						"name": "specificepithet",
						"type": "String"
					},
					{
						"name": "infraspecificepithet",
						"type": "String"
					},
					{
						"name": "verbatimtaxonrank",
						"type": "String"
					},
					{
						"name": "scientificnameauthorship",
						"type": "String"
					},
					{
						"name": "vernacularname",
						"type": "String"
					},
					{
						"name": "nomenclaturalcode",
						"type": "String"
					},
					{
						"name": "taxonomicstatus",
						"type": "String"
					},
					{
						"name": "nomenclaturalstatus",
						"type": "String"
					},
					{
						"name": "taxonremarks",
						"type": "String"
					}
				]
			},
			"dependsOn": [
				"[concat(variables('workspaceId'), '/linkedServices/oceananalyticsproject-WorkspaceDefaultStorage')]"
			]
		},
		{
			"name": "[concat(parameters('workspaceName'), '/WhalesTestCsv')]",
			"type": "Microsoft.Synapse/workspaces/datasets",
			"apiVersion": "2019-06-01-preview",
			"properties": {
				"linkedServiceName": {
					"referenceName": "oceananalyticsproject-WorkspaceDefaultStorage",
					"type": "LinkedServiceReference"
				},
				"annotations": [],
				"type": "DelimitedText",
				"typeProperties": {
					"location": {
						"type": "AzureBlobFSLocation",
						"fileName": "OccurrenceSmallTest.csv",
						"fileSystem": "ocean-analytics"
					},
					"columnDelimiter": ",",
					"escapeChar": "\\",
					"firstRowAsHeader": true,
					"quoteChar": "\""
				},
				"schema": [
					{
						"name": "id",
						"type": "String"
					},
					{
						"name": "dataset_id",
						"type": "String"
					},
					{
						"name": "decimallongitude",
						"type": "String"
					},
					{
						"name": "decimallatitude",
						"type": "String"
					},
					{
						"name": "date_start",
						"type": "String"
					},
					{
						"name": "date_mid",
						"type": "String"
					},
					{
						"name": "date_end",
						"type": "String"
					},
					{
						"name": "date_year",
						"type": "String"
					},
					{
						"name": "scientificname",
						"type": "String"
					},
					{
						"name": "originalscientificname",
						"type": "String"
					},
					{
						"name": "minimumdepthinmeters",
						"type": "String"
					},
					{
						"name": "maximumdepthinmeters",
						"type": "String"
					},
					{
						"name": "depth",
						"type": "String"
					},
					{
						"name": "coordinateuncertaintyinmeters",
						"type": "String"
					},
					{
						"name": "flags",
						"type": "String"
					},
					{
						"name": "dropped",
						"type": "String"
					},
					{
						"name": "absence",
						"type": "String"
					},
					{
						"name": "shoredistance",
						"type": "String"
					},
					{
						"name": "bathymetry",
						"type": "String"
					},
					{
						"name": "sst",
						"type": "String"
					},
					{
						"name": "sss",
						"type": "String"
					},
					{
						"name": "marine",
						"type": "String"
					},
					{
						"name": "brackish",
						"type": "String"
					},
					{
						"name": "freshwater",
						"type": "String"
					},
					{
						"name": "terrestrial",
						"type": "String"
					},
					{
						"name": "taxonrank",
						"type": "String"
					},
					{
						"name": "aphiaid",
						"type": "String"
					},
					{
						"name": "redlist_category",
						"type": "String"
					},
					{
						"name": "superdomain",
						"type": "String"
					},
					{
						"name": "domain",
						"type": "String"
					},
					{
						"name": "kingdom",
						"type": "String"
					},
					{
						"name": "subkingdom",
						"type": "String"
					},
					{
						"name": "infrakingdom",
						"type": "String"
					},
					{
						"name": "phylum",
						"type": "String"
					},
					{
						"name": "phylum_division",
						"type": "String"
					},
					{
						"name": "subphylum_subdivision",
						"type": "String"
					},
					{
						"name": "subphylum",
						"type": "String"
					},
					{
						"name": "infraphylum",
						"type": "String"
					},
					{
						"name": "parvphylum",
						"type": "String"
					},
					{
						"name": "gigaclass",
						"type": "String"
					},
					{
						"name": "megaclass",
						"type": "String"
					},
					{
						"name": "superclass",
						"type": "String"
					},
					{
						"name": "class",
						"type": "String"
					},
					{
						"name": "subclass",
						"type": "String"
					},
					{
						"name": "infraclass",
						"type": "String"
					},
					{
						"name": "subterclass",
						"type": "String"
					},
					{
						"name": "superorder",
						"type": "String"
					},
					{
						"name": "order",
						"type": "String"
					},
					{
						"name": "suborder",
						"type": "String"
					},
					{
						"name": "infraorder",
						"type": "String"
					},
					{
						"name": "parvorder",
						"type": "String"
					},
					{
						"name": "superfamily",
						"type": "String"
					},
					{
						"name": "family",
						"type": "String"
					},
					{
						"name": "subfamily",
						"type": "String"
					},
					{
						"name": "supertribe",
						"type": "String"
					},
					{
						"name": "tribe",
						"type": "String"
					},
					{
						"name": "subtribe",
						"type": "String"
					},
					{
						"name": "genus",
						"type": "String"
					},
					{
						"name": "subgenus",
						"type": "String"
					},
					{
						"name": "section",
						"type": "String"
					},
					{
						"name": "subsection",
						"type": "String"
					},
					{
						"name": "series",
						"type": "String"
					},
					{
						"name": "species",
						"type": "String"
					},
					{
						"name": "subspecies",
						"type": "String"
					},
					{
						"name": "natio",
						"type": "String"
					},
					{
						"name": "variety",
						"type": "String"
					},
					{
						"name": "subvariety",
						"type": "String"
					},
					{
						"name": "forma",
						"type": "String"
					},
					{
						"name": "subforma",
						"type": "String"
					},
					{
						"name": "type",
						"type": "String"
					},
					{
						"name": "modified",
						"type": "String"
					},
					{
						"name": "language",
						"type": "String"
					},
					{
						"name": "license",
						"type": "String"
					},
					{
						"name": "rightsholder",
						"type": "String"
					},
					{
						"name": "accessrights",
						"type": "String"
					},
					{
						"name": "bibliographiccitation",
						"type": "String"
					},
					{
						"name": "references",
						"type": "String"
					},
					{
						"name": "institutionid",
						"type": "String"
					},
					{
						"name": "collectionid",
						"type": "String"
					},
					{
						"name": "datasetid",
						"type": "String"
					},
					{
						"name": "institutioncode",
						"type": "String"
					},
					{
						"name": "collectioncode",
						"type": "String"
					},
					{
						"name": "datasetname",
						"type": "String"
					},
					{
						"name": "ownerinstitutioncode",
						"type": "String"
					},
					{
						"name": "basisofrecord",
						"type": "String"
					},
					{
						"name": "informationwithheld",
						"type": "String"
					},
					{
						"name": "datageneralizations",
						"type": "String"
					},
					{
						"name": "dynamicproperties",
						"type": "String"
					},
					{
						"name": "materialsampleid",
						"type": "String"
					},
					{
						"name": "occurrenceid",
						"type": "String"
					},
					{
						"name": "catalognumber",
						"type": "String"
					},
					{
						"name": "occurrenceremarks",
						"type": "String"
					},
					{
						"name": "recordnumber",
						"type": "String"
					},
					{
						"name": "recordedby",
						"type": "String"
					},
					{
						"name": "recordedbyid",
						"type": "String"
					},
					{
						"name": "individualcount",
						"type": "String"
					},
					{
						"name": "organismquantity",
						"type": "String"
					},
					{
						"name": "organismquantitytype",
						"type": "String"
					},
					{
						"name": "sex",
						"type": "String"
					},
					{
						"name": "lifestage",
						"type": "String"
					},
					{
						"name": "reproductivecondition",
						"type": "String"
					},
					{
						"name": "behavior",
						"type": "String"
					},
					{
						"name": "establishmentmeans",
						"type": "String"
					},
					{
						"name": "occurrencestatus",
						"type": "String"
					},
					{
						"name": "preparations",
						"type": "String"
					},
					{
						"name": "disposition",
						"type": "String"
					},
					{
						"name": "othercatalognumbers",
						"type": "String"
					},
					{
						"name": "associatedmedia",
						"type": "String"
					},
					{
						"name": "associatedreferences",
						"type": "String"
					},
					{
						"name": "associatedsequences",
						"type": "String"
					},
					{
						"name": "associatedtaxa",
						"type": "String"
					},
					{
						"name": "organismid",
						"type": "String"
					},
					{
						"name": "organismname",
						"type": "String"
					},
					{
						"name": "organismscope",
						"type": "String"
					},
					{
						"name": "associatedoccurrences",
						"type": "String"
					},
					{
						"name": "associatedorganisms",
						"type": "String"
					},
					{
						"name": "previousidentifications",
						"type": "String"
					},
					{
						"name": "organismremarks",
						"type": "String"
					},
					{
						"name": "eventid",
						"type": "String"
					},
					{
						"name": "parenteventid",
						"type": "String"
					},
					{
						"name": "samplingprotocol",
						"type": "String"
					},
					{
						"name": "samplesizevalue",
						"type": "String"
					},
					{
						"name": "samplesizeunit",
						"type": "String"
					},
					{
						"name": "samplingeffort",
						"type": "String"
					},
					{
						"name": "eventdate",
						"type": "String"
					},
					{
						"name": "eventtime",
						"type": "String"
					},
					{
						"name": "startdayofyear",
						"type": "String"
					},
					{
						"name": "enddayofyear",
						"type": "String"
					},
					{
						"name": "year",
						"type": "String"
					},
					{
						"name": "month",
						"type": "String"
					},
					{
						"name": "day",
						"type": "String"
					},
					{
						"name": "verbatimeventdate",
						"type": "String"
					},
					{
						"name": "habitat",
						"type": "String"
					},
					{
						"name": "fieldnumber",
						"type": "String"
					},
					{
						"name": "fieldnotes",
						"type": "String"
					},
					{
						"name": "eventremarks",
						"type": "String"
					},
					{
						"name": "locationid",
						"type": "String"
					},
					{
						"name": "highergeographyid",
						"type": "String"
					},
					{
						"name": "highergeography",
						"type": "String"
					},
					{
						"name": "continent",
						"type": "String"
					},
					{
						"name": "waterbody",
						"type": "String"
					},
					{
						"name": "islandgroup",
						"type": "String"
					},
					{
						"name": "island",
						"type": "String"
					},
					{
						"name": "country",
						"type": "String"
					},
					{
						"name": "countrycode",
						"type": "String"
					},
					{
						"name": "stateprovince",
						"type": "String"
					},
					{
						"name": "county",
						"type": "String"
					},
					{
						"name": "municipality",
						"type": "String"
					},
					{
						"name": "locality",
						"type": "String"
					},
					{
						"name": "verbatimlocality",
						"type": "String"
					},
					{
						"name": "verbatimelevation",
						"type": "String"
					},
					{
						"name": "minimumelevationinmeters",
						"type": "String"
					},
					{
						"name": "maximumelevationinmeters",
						"type": "String"
					},
					{
						"name": "verbatimdepth",
						"type": "String"
					},
					{
						"name": "minimumdistanceabovesurfaceinmeters",
						"type": "String"
					},
					{
						"name": "maximumdistanceabovesurfaceinmeters",
						"type": "String"
					},
					{
						"name": "locationaccordingto",
						"type": "String"
					},
					{
						"name": "locationremarks",
						"type": "String"
					},
					{
						"name": "verbatimcoordinates",
						"type": "String"
					},
					{
						"name": "verbatimlatitude",
						"type": "String"
					},
					{
						"name": "verbatimlongitude",
						"type": "String"
					},
					{
						"name": "verbatimcoordinatesystem",
						"type": "String"
					},
					{
						"name": "verbatimsrs",
						"type": "String"
					},
					{
						"name": "geodeticdatum",
						"type": "String"
					},
					{
						"name": "coordinateprecision",
						"type": "String"
					},
					{
						"name": "pointradiusspatialfit",
						"type": "String"
					},
					{
						"name": "footprintwkt",
						"type": "String"
					},
					{
						"name": "footprintsrs",
						"type": "String"
					},
					{
						"name": "footprintspatialfit",
						"type": "String"
					},
					{
						"name": "georeferencedby",
						"type": "String"
					},
					{
						"name": "georeferenceddate",
						"type": "String"
					},
					{
						"name": "georeferenceprotocol",
						"type": "String"
					},
					{
						"name": "georeferencesources",
						"type": "String"
					},
					{
						"name": "georeferenceverificationstatus",
						"type": "String"
					},
					{
						"name": "georeferenceremarks",
						"type": "String"
					},
					{
						"name": "geologicalcontextid",
						"type": "String"
					},
					{
						"name": "earliesteonorlowesteonothem",
						"type": "String"
					},
					{
						"name": "latesteonorhighesteonothem",
						"type": "String"
					},
					{
						"name": "earliesteraorlowesterathem",
						"type": "String"
					},
					{
						"name": "latesteraorhighesterathem",
						"type": "String"
					},
					{
						"name": "earliestperiodorlowestsystem",
						"type": "String"
					},
					{
						"name": "latestperiodorhighestsystem",
						"type": "String"
					},
					{
						"name": "earliestepochorlowestseries",
						"type": "String"
					},
					{
						"name": "latestepochorhighestseries",
						"type": "String"
					},
					{
						"name": "earliestageorloweststage",
						"type": "String"
					},
					{
						"name": "latestageorhigheststage",
						"type": "String"
					},
					{
						"name": "lowestbiostratigraphiczone",
						"type": "String"
					},
					{
						"name": "highestbiostratigraphiczone",
						"type": "String"
					},
					{
						"name": "lithostratigraphicterms",
						"type": "String"
					},
					{
						"name": "group",
						"type": "String"
					},
					{
						"name": "formation",
						"type": "String"
					},
					{
						"name": "member",
						"type": "String"
					},
					{
						"name": "bed",
						"type": "String"
					},
					{
						"name": "identificationid",
						"type": "String"
					},
					{
						"name": "identifiedby",
						"type": "String"
					},
					{
						"name": "identifiedbyid",
						"type": "String"
					},
					{
						"name": "dateidentified",
						"type": "String"
					},
					{
						"name": "identificationreferences",
						"type": "String"
					},
					{
						"name": "identificationremarks",
						"type": "String"
					},
					{
						"name": "identificationqualifier",
						"type": "String"
					},
					{
						"name": "identificationverificationstatus",
						"type": "String"
					},
					{
						"name": "typestatus",
						"type": "String"
					},
					{
						"name": "taxonid",
						"type": "String"
					},
					{
						"name": "scientificnameid",
						"type": "String"
					},
					{
						"name": "acceptednameusageid",
						"type": "String"
					},
					{
						"name": "parentnameusageid",
						"type": "String"
					},
					{
						"name": "originalnameusageid",
						"type": "String"
					},
					{
						"name": "nameaccordingtoid",
						"type": "String"
					},
					{
						"name": "namepublishedinid",
						"type": "String"
					},
					{
						"name": "taxonconceptid",
						"type": "String"
					},
					{
						"name": "acceptednameusage",
						"type": "String"
					},
					{
						"name": "parentnameusage",
						"type": "String"
					},
					{
						"name": "originalnameusage",
						"type": "String"
					},
					{
						"name": "nameaccordingto",
						"type": "String"
					},
					{
						"name": "namepublishedin",
						"type": "String"
					},
					{
						"name": "namepublishedinyear",
						"type": "String"
					},
					{
						"name": "higherclassification",
						"type": "String"
					},
					{
						"name": "specificepithet",
						"type": "String"
					},
					{
						"name": "infraspecificepithet",
						"type": "String"
					},
					{
						"name": "verbatimtaxonrank",
						"type": "String"
					},
					{
						"name": "scientificnameauthorship",
						"type": "String"
					},
					{
						"name": "vernacularname",
						"type": "String"
					},
					{
						"name": "nomenclaturalcode",
						"type": "String"
					},
					{
						"name": "taxonomicstatus",
						"type": "String"
					},
					{
						"name": "nomenclaturalstatus",
						"type": "String"
					},
					{
						"name": "taxonremarks",
						"type": "String"
					}
				]
			},
			"dependsOn": [
				"[concat(variables('workspaceId'), '/linkedServices/oceananalyticsproject-WorkspaceDefaultStorage')]"
			]
		},
		{
			"name": "[concat(parameters('workspaceName'), '/AzureDataLakeStorage1')]",
			"type": "Microsoft.Synapse/workspaces/linkedServices",
			"apiVersion": "2019-06-01-preview",
			"properties": {
				"annotations": [],
				"type": "AzureBlobFS",
				"typeProperties": {
					"url": "[parameters('AzureDataLakeStorage1_properties_typeProperties_url')]",
					"accountKey": {
						"type": "SecureString",
						"value": "[parameters('AzureDataLakeStorage1_accountKey')]"
					}
				},
				"connectVia": {
					"referenceName": "AutoResolveIntegrationRuntime",
					"type": "IntegrationRuntimeReference"
				}
			},
			"dependsOn": [
				"[concat(variables('workspaceId'), '/integrationRuntimes/AutoResolveIntegrationRuntime')]"
			]
		},
		{
			"name": "[concat(parameters('workspaceName'), '/AzureSynapseAnalytics1')]",
			"type": "Microsoft.Synapse/workspaces/linkedServices",
			"apiVersion": "2019-06-01-preview",
			"properties": {
				"annotations": [],
				"type": "AzureSqlDW",
				"typeProperties": {
					"server": "[parameters('AzureSynapseAnalytics1_properties_typeProperties_server')]",
					"database": "[parameters('AzureSynapseAnalytics1_properties_typeProperties_database')]",
					"encrypt": "mandatory",
					"trustServerCertificate": false,
					"authenticationType": "SQL",
					"userName": "[parameters('AzureSynapseAnalytics1_properties_typeProperties_userName')]",
					"password": {
						"type": "SecureString",
						"value": "[parameters('AzureSynapseAnalytics1_password')]"
					}
				},
				"connectVia": {
					"referenceName": "AutoResolveIntegrationRuntime",
					"type": "IntegrationRuntimeReference"
				}
			},
			"dependsOn": [
				"[concat(variables('workspaceId'), '/integrationRuntimes/AutoResolveIntegrationRuntime')]"
			]
		},
		{
			"name": "[concat(parameters('workspaceName'), '/CosmosDbNoSql_External')]",
			"type": "Microsoft.Synapse/workspaces/linkedServices",
			"apiVersion": "2019-06-01-preview",
			"properties": {
				"annotations": [],
				"type": "CosmosDb",
				"typeProperties": {
					"connectionString": "[parameters('CosmosDbNoSql_External_connectionString')]"
				},
				"connectVia": {
					"referenceName": "AutoResolveIntegrationRuntime",
					"type": "IntegrationRuntimeReference"
				}
			},
			"dependsOn": [
				"[concat(variables('workspaceId'), '/integrationRuntimes/AutoResolveIntegrationRuntime')]"
			]
		},
		{
			"name": "[concat(parameters('workspaceName'), '/OceanAnalytics_CosmosDbNoSql')]",
			"type": "Microsoft.Synapse/workspaces/linkedServices",
			"apiVersion": "2019-06-01-preview",
			"properties": {
				"annotations": [],
				"type": "CosmosDb",
				"typeProperties": {
					"connectionString": "[parameters('OceanAnalytics_CosmosDbNoSql_connectionString')]"
				},
				"connectVia": {
					"referenceName": "AutoResolveIntegrationRuntime",
					"type": "IntegrationRuntimeReference"
				}
			},
			"dependsOn": [
				"[concat(variables('workspaceId'), '/integrationRuntimes/AutoResolveIntegrationRuntime')]"
			]
		},
		{
			"name": "[concat(parameters('workspaceName'), '/PowerBIOceanWorkspace')]",
			"type": "Microsoft.Synapse/workspaces/linkedServices",
			"apiVersion": "2019-06-01-preview",
			"properties": {
				"annotations": [],
				"type": "PowerBIWorkspace",
				"typeProperties": {
					"tenantID": "017e2a90-2946-4c75-9dc7-55fcf23627c9"
				}
			},
			"dependsOn": []
		},
		{
			"name": "[concat(parameters('workspaceName'), '/WhalesApi_Linked_Service')]",
			"type": "Microsoft.Synapse/workspaces/linkedServices",
			"apiVersion": "2019-06-01-preview",
			"properties": {
				"annotations": [],
				"type": "RestService",
				"typeProperties": {
					"url": "[parameters('WhalesApi_Linked_Service_properties_typeProperties_url')]",
					"enableServerCertificateValidation": false,
					"authenticationType": "Anonymous"
				},
				"connectVia": {
					"referenceName": "AutoResolveIntegrationRuntime",
					"type": "IntegrationRuntimeReference"
				}
			},
			"dependsOn": [
				"[concat(variables('workspaceId'), '/integrationRuntimes/AutoResolveIntegrationRuntime')]"
			]
		},
		{
			"name": "[concat(parameters('workspaceName'), '/oceananalyticsproject-WorkspaceDefaultSqlServer')]",
			"type": "Microsoft.Synapse/workspaces/linkedServices",
			"apiVersion": "2019-06-01-preview",
			"properties": {
				"parameters": {
					"DBName": {
						"type": "String"
					}
				},
				"annotations": [],
				"type": "AzureSqlDW",
				"typeProperties": {
					"connectionString": "[parameters('oceananalyticsproject-WorkspaceDefaultSqlServer_connectionString')]"
				},
				"connectVia": {
					"referenceName": "AutoResolveIntegrationRuntime",
					"type": "IntegrationRuntimeReference"
				}
			},
			"dependsOn": [
				"[concat(variables('workspaceId'), '/integrationRuntimes/AutoResolveIntegrationRuntime')]"
			]
		},
		{
			"name": "[concat(parameters('workspaceName'), '/oceananalyticsproject-WorkspaceDefaultStorage')]",
			"type": "Microsoft.Synapse/workspaces/linkedServices",
			"apiVersion": "2019-06-01-preview",
			"properties": {
				"annotations": [],
				"type": "AzureBlobFS",
				"typeProperties": {
					"url": "[parameters('oceananalyticsproject-WorkspaceDefaultStorage_properties_typeProperties_url')]"
				},
				"connectVia": {
					"referenceName": "AutoResolveIntegrationRuntime",
					"type": "IntegrationRuntimeReference"
				}
			},
			"dependsOn": [
				"[concat(variables('workspaceId'), '/integrationRuntimes/AutoResolveIntegrationRuntime')]"
			]
		},
		{
			"name": "[concat(parameters('workspaceName'), '/AutoResolveIntegrationRuntime')]",
			"type": "Microsoft.Synapse/workspaces/integrationRuntimes",
			"apiVersion": "2019-06-01-preview",
			"properties": {
				"type": "Managed",
				"typeProperties": {
					"computeProperties": {
						"location": "AutoResolve",
						"dataFlowProperties": {
							"computeType": "General",
							"coreCount": 8,
							"timeToLive": 0
						}
					}
				}
			},
			"dependsOn": []
		},
		{
			"name": "[concat(parameters('workspaceName'), '/CosmoDbToObisWhalesSampleDB')]",
			"type": "Microsoft.Synapse/workspaces/dataflows",
			"apiVersion": "2019-06-01-preview",
			"properties": {
				"type": "MappingDataFlow",
				"typeProperties": {
					"sources": [
						{
							"linkedService": {
								"referenceName": "OceanAnalytics_CosmosDbNoSql",
								"type": "LinkedServiceReference"
							},
							"name": "CosmosDbSql"
						}
					],
					"sinks": [
						{
							"name": "SampleDataBase"
						}
					],
					"transformations": [],
					"scriptLines": [
						"source(allowSchemaDrift: true,",
						"     validateSchema: false,",
						"     limit: 10000,",
						"     container: 'whales_analytical_store',",
						"     storeType: 'olap',",
						"     format: 'documentQuery',",
						"     query: 'SELECT *\\nFROM c\\nWHERE c.scientific_name IN (\\n    SELECT c.scientific_name\\n    FROM c\\n    GROUP BY c.scientific_name\\n    HAVING COUNT(1) > 50000\\n)',",
						"     enableChangeFeed: true,",
						"     changeFeedStartFromTheBeginning: true,",
						"     captureIntermediateUpdate: false,",
						"     captureUserDeletes: true,",
						"     captureTxnTTLDeletes: true,",
						"     preferredRegions: ['France Central'],",
						"     store: 'cosmosDB') ~> CosmosDbSql",
						"CosmosDbSql sink(allowSchemaDrift: true,",
						"     validateSchema: false,",
						"     store: 'synapse',",
						"     databaseType: 'spark',",
						"     format: 'table',",
						"     database: 'OBIS',",
						"     tableName: 'WhaleSampleDataSql',",
						"     recreate:true) ~> SampleDataBase"
					]
				}
			},
			"dependsOn": [
				"[concat(variables('workspaceId'), '/linkedServices/OceanAnalytics_CosmosDbNoSql')]"
			]
		},
		{
			"name": "[concat(parameters('workspaceName'), '/WhalesCsvToMongoDbTest')]",
			"type": "Microsoft.Synapse/workspaces/dataflows",
			"apiVersion": "2019-06-01-preview",
			"properties": {
				"type": "MappingDataFlow",
				"typeProperties": {
					"sources": [
						{
							"dataset": {
								"referenceName": "WhalesOccurence_Prod",
								"type": "DatasetReference"
							},
							"name": "WhalesCsv"
						}
					],
					"sinks": [
						{
							"linkedService": {
								"referenceName": "OceanAnalytics_CosmosDbNoSql",
								"type": "LinkedServiceReference"
							},
							"name": "exporttocosmodb"
						}
					],
					"transformations": [
						{
							"name": "idgenerate"
						},
						{
							"name": "selectcolumns"
						},
						{
							"name": "filterdatescientificnamelocation"
						},
						{
							"name": "timestamptodatetime"
						}
					],
					"scriptLines": [
						"source(output(",
						"          id as string,",
						"          dataset_id as string,",
						"          decimallongitude as string,",
						"          decimallatitude as string,",
						"          date_start as string,",
						"          date_mid as string,",
						"          date_end as string,",
						"          date_year as string,",
						"          scientificname as string,",
						"          originalscientificname as string,",
						"          minimumdepthinmeters as string,",
						"          maximumdepthinmeters as string,",
						"          depth as string,",
						"          coordinateuncertaintyinmeters as string,",
						"          flags as string,",
						"          dropped as string,",
						"          absence as string,",
						"          shoredistance as string,",
						"          bathymetry as string,",
						"          sst as string,",
						"          sss as string,",
						"          marine as string,",
						"          brackish as string,",
						"          freshwater as string,",
						"          terrestrial as string,",
						"          taxonrank as string,",
						"          aphiaid as string,",
						"          redlist_category as string,",
						"          superdomain as string,",
						"          domain as string,",
						"          kingdom as string,",
						"          subkingdom as string,",
						"          infrakingdom as string,",
						"          phylum as string,",
						"          phylum_division as string,",
						"          subphylum_subdivision as string,",
						"          subphylum as string,",
						"          infraphylum as string,",
						"          parvphylum as string,",
						"          gigaclass as string,",
						"          megaclass as string,",
						"          superclass as string,",
						"          class as string,",
						"          subclass as string,",
						"          infraclass as string,",
						"          subterclass as string,",
						"          superorder as string,",
						"          order as string,",
						"          suborder as string,",
						"          infraorder as string,",
						"          parvorder as string,",
						"          superfamily as string,",
						"          family as string,",
						"          subfamily as string,",
						"          supertribe as string,",
						"          tribe as string,",
						"          subtribe as string,",
						"          genus as string,",
						"          subgenus as string,",
						"          section as string,",
						"          subsection as string,",
						"          series as string,",
						"          species as string,",
						"          subspecies as string,",
						"          natio as string,",
						"          variety as string,",
						"          subvariety as string,",
						"          forma as string,",
						"          subforma as string,",
						"          type as string,",
						"          modified as string,",
						"          language as string,",
						"          license as string,",
						"          rightsholder as string,",
						"          accessrights as string,",
						"          bibliographiccitation as string,",
						"          references as string,",
						"          institutionid as string,",
						"          collectionid as string,",
						"          datasetid as string,",
						"          institutioncode as string,",
						"          collectioncode as string,",
						"          datasetname as string,",
						"          ownerinstitutioncode as string,",
						"          basisofrecord as string,",
						"          informationwithheld as string,",
						"          datageneralizations as string,",
						"          dynamicproperties as string,",
						"          materialsampleid as string,",
						"          occurrenceid as string,",
						"          catalognumber as string,",
						"          occurrenceremarks as string,",
						"          recordnumber as string,",
						"          recordedby as string,",
						"          recordedbyid as string,",
						"          individualcount as string,",
						"          organismquantity as string,",
						"          organismquantitytype as string,",
						"          sex as string,",
						"          lifestage as string,",
						"          reproductivecondition as string,",
						"          behavior as string,",
						"          establishmentmeans as string,",
						"          occurrencestatus as string,",
						"          preparations as string,",
						"          disposition as string,",
						"          othercatalognumbers as string,",
						"          associatedmedia as string,",
						"          associatedreferences as string,",
						"          associatedsequences as string,",
						"          associatedtaxa as string,",
						"          organismid as string,",
						"          organismname as string,",
						"          organismscope as string,",
						"          associatedoccurrences as string,",
						"          associatedorganisms as string,",
						"          previousidentifications as string,",
						"          organismremarks as string,",
						"          eventid as string,",
						"          parenteventid as string,",
						"          samplingprotocol as string,",
						"          samplesizevalue as string,",
						"          samplesizeunit as string,",
						"          samplingeffort as string,",
						"          eventdate as string,",
						"          eventtime as string,",
						"          startdayofyear as string,",
						"          enddayofyear as string,",
						"          year as string,",
						"          month as string,",
						"          day as string,",
						"          verbatimeventdate as string,",
						"          habitat as string,",
						"          fieldnumber as string,",
						"          fieldnotes as string,",
						"          eventremarks as string,",
						"          locationid as string,",
						"          highergeographyid as string,",
						"          highergeography as string,",
						"          continent as string,",
						"          waterbody as string,",
						"          islandgroup as string,",
						"          island as string,",
						"          country as string,",
						"          countrycode as string,",
						"          stateprovince as string,",
						"          county as string,",
						"          municipality as string,",
						"          locality as string,",
						"          verbatimlocality as string,",
						"          verbatimelevation as string,",
						"          minimumelevationinmeters as string,",
						"          maximumelevationinmeters as string,",
						"          verbatimdepth as string,",
						"          minimumdistanceabovesurfaceinmeters as string,",
						"          maximumdistanceabovesurfaceinmeters as string,",
						"          locationaccordingto as string,",
						"          locationremarks as string,",
						"          verbatimcoordinates as string,",
						"          verbatimlatitude as string,",
						"          verbatimlongitude as string,",
						"          verbatimcoordinatesystem as string,",
						"          verbatimsrs as string,",
						"          geodeticdatum as string,",
						"          coordinateprecision as string,",
						"          pointradiusspatialfit as string,",
						"          footprintwkt as string,",
						"          footprintsrs as string,",
						"          footprintspatialfit as string,",
						"          georeferencedby as string,",
						"          georeferenceddate as string,",
						"          georeferenceprotocol as string,",
						"          georeferencesources as string,",
						"          georeferenceverificationstatus as string,",
						"          georeferenceremarks as string,",
						"          geologicalcontextid as string,",
						"          earliesteonorlowesteonothem as string,",
						"          latesteonorhighesteonothem as string,",
						"          earliesteraorlowesterathem as string,",
						"          latesteraorhighesterathem as string,",
						"          earliestperiodorlowestsystem as string,",
						"          latestperiodorhighestsystem as string,",
						"          earliestepochorlowestseries as string,",
						"          latestepochorhighestseries as string,",
						"          earliestageorloweststage as string,",
						"          latestageorhigheststage as string,",
						"          lowestbiostratigraphiczone as string,",
						"          highestbiostratigraphiczone as string,",
						"          lithostratigraphicterms as string,",
						"          group as string,",
						"          formation as string,",
						"          member as string,",
						"          bed as string,",
						"          identificationid as string,",
						"          identifiedby as string,",
						"          identifiedbyid as string,",
						"          dateidentified as string,",
						"          identificationreferences as string,",
						"          identificationremarks as string,",
						"          identificationqualifier as string,",
						"          identificationverificationstatus as string,",
						"          typestatus as string,",
						"          taxonid as string,",
						"          scientificnameid as string,",
						"          acceptednameusageid as string,",
						"          parentnameusageid as string,",
						"          originalnameusageid as string,",
						"          nameaccordingtoid as string,",
						"          namepublishedinid as string,",
						"          taxonconceptid as string,",
						"          acceptednameusage as string,",
						"          parentnameusage as string,",
						"          originalnameusage as string,",
						"          nameaccordingto as string,",
						"          namepublishedin as string,",
						"          namepublishedinyear as string,",
						"          higherclassification as string,",
						"          specificepithet as string,",
						"          infraspecificepithet as string,",
						"          verbatimtaxonrank as string,",
						"          scientificnameauthorship as string,",
						"          vernacularname as string,",
						"          nomenclaturalcode as string,",
						"          taxonomicstatus as string,",
						"          nomenclaturalstatus as string,",
						"          taxonremarks as string",
						"     ),",
						"     allowSchemaDrift: true,",
						"     validateSchema: false,",
						"     ignoreNoFilesFound: true,",
						"     maxColumns: 1000) ~> WhalesCsv",
						"timestamptodatetime derive(id = uuid()) ~> idgenerate",
						"WhalesCsv select(mapColumn(",
						"          internal_id = id,",
						"          scientific_name = scientificname,",
						"          depth,",
						"          is_deleted = absence,",
						"          latitude = decimallatitude,",
						"          longitude = decimallongitude,",
						"          locality,",
						"          minimum_depth_in_meters = minimumdepthinmeters,",
						"          maximum_depth_in_meters = maximumdepthinmeters,",
						"          record_way = basisofrecord,",
						"          shore_distance = shoredistance,",
						"          event_date = date_start",
						"     ),",
						"     skipDuplicateMapInputs: true,",
						"     skipDuplicateMapOutputs: true) ~> selectcolumns",
						"selectcolumns filter(!isNull(event_date) && !isNull(scientific_name) && !isNull(latitude) && !isNull(longitude)) ~> filterdatescientificnamelocation",
						"filterdatescientificnamelocation derive(event_date = toLong(event_date) / 1000) ~> timestamptodatetime",
						"idgenerate sink(allowSchemaDrift: true,",
						"     validateSchema: false,",
						"     format: 'document',",
						"     container: 'whales_analytical_store',",
						"     deletable: false,",
						"     insertable: true,",
						"     updateable: false,",
						"     upsertable: true,",
						"     partitionKey: ['/scientific_name/internal_id'],",
						"     store: 'cosmosDB',",
						"     skipDuplicateMapInputs: true,",
						"     skipDuplicateMapOutputs: true,",
						"     preCommands: [],",
						"     postCommands: []) ~> exporttocosmodb"
					]
				}
			},
			"dependsOn": [
				"[concat(variables('workspaceId'), '/datasets/WhalesOccurence_Prod')]",
				"[concat(variables('workspaceId'), '/linkedServices/OceanAnalytics_CosmosDbNoSql')]"
			]
		},
		{
			"name": "[concat(parameters('workspaceName'), '/WorkspaceSystemIdentity')]",
			"type": "Microsoft.Synapse/workspaces/credentials",
			"apiVersion": "2019-06-01-preview",
			"properties": {
				"type": "ManagedIdentity",
				"typeProperties": {}
			},
			"dependsOn": []
		},
		{
			"name": "[concat(parameters('workspaceName'), '/SQL script 2')]",
			"type": "Microsoft.Synapse/workspaces/sqlscripts",
			"apiVersion": "2019-06-01-preview",
			"properties": {
				"content": {
					"query": "CREATE TABLE WhaleSampleDataSql (\n    id VARCHAR(255),\n    scientific_name VARCHAR(255),\n    depth VARCHAR(10),\n    is_deleted VARCHAR(10),\n    latitude VARCHAR(20),\n    longitude VARCHAR(20),\n    locality VARCHAR(255),\n    maximum_depth_in_meters VARCHAR(20),\n    minimum_depth_in_meters VARCHAR(20),\n    record_way VARCHAR(255),\n    shore_distance VARCHAR(20)\n)",
					"metadata": {
						"language": "sql"
					},
					"currentConnection": {
						"databaseName": "OBIS",
						"poolName": "Built-in"
					},
					"resultLimit": 5000
				},
				"type": "SqlQuery"
			},
			"dependsOn": []
		},
		{
			"name": "[concat(parameters('workspaceName'), '/OBIS')]",
			"type": "Microsoft.Synapse/workspaces/databases",
			"apiVersion": "2019-06-01-preview",
			"properties": {
				"Ddls": [
					{
						"ActionType": "CREATE",
						"OldEntity": null,
						"NewEntity": {
							"Name": "OBIS",
							"EntityType": "DATABASE",
							"Origin": {
								"Type": "SPARK"
							},
							"Properties": {
								"IsSyMSCDMDatabase": true
							},
							"Source": {
								"Provider": "ADLS",
								"Location": "abfss://ocean-analytics@extremmapstorageaccount.dfs.core.windows.net/OBIS",
								"Properties": {
									"FormatType": "csv",
									"LinkedServiceName": "oceananalyticsproject-WorkspaceDefaultStorage"
								}
							},
							"PublishStatus": "PUBLISHED",
							"ObjectVersion": 2,
							"ObjectId": "dbd9346b-ebe7-4a37-85f9-579d0774879b"
						},
						"Source": {
							"Type": "SPARK"
						}
					},
					{
						"ActionType": "CREATE",
						"OldEntity": null,
						"NewEntity": {
							"Name": "WhaleSampleDataSql",
							"EntityType": "TABLE",
							"Namespace": {
								"DatabaseName": "OBIS"
							},
							"Description": "",
							"TableType": "EXTERNAL",
							"Origin": {
								"Type": "SPARK"
							},
							"StorageDescriptor": {
								"Columns": [
									{
										"Name": "id",
										"OriginDataTypeName": {
											"TypeName": "string",
											"IsComplexType": false,
											"IsNullable": false,
											"Length": 256,
											"Properties": {
												"HIVE_TYPE_STRING": "string"
											}
										}
									},
									{
										"Name": "scientific_name",
										"Description": "",
										"OriginDataTypeName": {
											"TypeName": "string",
											"IsComplexType": false,
											"IsNullable": true,
											"Length": 256,
											"Properties": {
												"HIVE_TYPE_STRING": "string"
											}
										}
									},
									{
										"Name": "depth",
										"Description": "",
										"OriginDataTypeName": {
											"TypeName": "string",
											"IsComplexType": false,
											"IsNullable": true,
											"Length": 256,
											"Properties": {
												"HIVE_TYPE_STRING": "string"
											}
										}
									},
									{
										"Name": "is_deleted",
										"Description": "",
										"OriginDataTypeName": {
											"TypeName": "string",
											"IsComplexType": false,
											"IsNullable": true,
											"Length": 20,
											"Properties": {
												"HIVE_TYPE_STRING": "string"
											}
										}
									},
									{
										"Name": "latitude",
										"Description": "",
										"OriginDataTypeName": {
											"TypeName": "string",
											"IsComplexType": false,
											"IsNullable": true,
											"Length": 20,
											"Properties": {
												"HIVE_TYPE_STRING": "string"
											}
										}
									},
									{
										"Name": "longitude",
										"Description": "",
										"OriginDataTypeName": {
											"TypeName": "string",
											"IsComplexType": false,
											"IsNullable": true,
											"Length": 20,
											"Properties": {
												"HIVE_TYPE_STRING": "string"
											}
										}
									},
									{
										"Name": "locality",
										"Description": "",
										"OriginDataTypeName": {
											"TypeName": "string",
											"IsComplexType": false,
											"IsNullable": true,
											"Length": 1000,
											"Properties": {
												"HIVE_TYPE_STRING": "string"
											}
										}
									},
									{
										"Name": "maximum_depth_in_meters",
										"Description": "",
										"OriginDataTypeName": {
											"TypeName": "string",
											"IsComplexType": false,
											"IsNullable": true,
											"Length": 20,
											"Properties": {
												"HIVE_TYPE_STRING": "string"
											}
										}
									},
									{
										"Name": "minimum_depth_in_meters",
										"Description": "",
										"OriginDataTypeName": {
											"TypeName": "string",
											"IsComplexType": false,
											"IsNullable": true,
											"Length": 20,
											"Properties": {
												"HIVE_TYPE_STRING": "string"
											}
										}
									},
									{
										"Name": "record_way",
										"Description": "",
										"OriginDataTypeName": {
											"TypeName": "string",
											"IsComplexType": false,
											"IsNullable": true,
											"Length": 1000,
											"Properties": {
												"HIVE_TYPE_STRING": "string"
											}
										}
									},
									{
										"Name": "shore_distance",
										"Description": "",
										"OriginDataTypeName": {
											"TypeName": "string",
											"IsComplexType": false,
											"IsNullable": true,
											"Length": 20,
											"Properties": {
												"HIVE_TYPE_STRING": "string"
											}
										}
									}
								],
								"Format": {
									"InputFormat": "org.apache.hadoop.hive.ql.io.parquet.MapredParquetInputFormat",
									"OutputFormat": "org.apache.hadoop.hive.ql.io.parquet.MapredParquetOutputFormat",
									"FormatType": "parquet",
									"SerializeLib": "org.apache.hadoop.hive.ql.io.parquet.serde.ParquetHiveSerDe",
									"Properties": {
										"path": "abfss://ocean-analytics@extremmapstorageaccount.dfs.core.windows.net/synapse/workspaces/OCEANANALYTICSPROJECT",
										"FormatTypeSetToDatabaseDefault": false
									}
								},
								"Source": {
									"Provider": "ADLS",
									"Location": "abfss://ocean-analytics@extremmapstorageaccount.dfs.core.windows.net/synapse/workspaces/OCEANANALYTICSPROJECT",
									"Properties": {
										"LinkedServiceName": "oceananalyticsproject-WorkspaceDefaultStorage",
										"LocationSetToDatabaseDefault": false
									}
								},
								"Properties": {
									"textinputformat.record.delimiter": ",",
									"compression": "{\"type\":\"None\",\"level\":\"optimal\"}",
									"derivedModelAttributeInfo": "{\"attributeReferences\":{}}"
								},
								"Compressed": false,
								"IsStoredAsSubdirectories": false
							},
							"Properties": {
								"Description": "",
								"DisplayFolderInfo": "{\"name\":\"Others\",\"colorCode\":\"\"}",
								"PrimaryKeys": "id",
								"spark.sql.sources.provider": "parquet",
								"sql:IsAppendOnly": true
							},
							"Retention": 0,
							"Temporary": false,
							"IsRewriteEnabled": false
						},
						"Source": {
							"Type": "SPARK"
						}
					}
				]
			},
			"dependsOn": []
		}
	]
}